[{"id":"1101142001","district_id":"110114","name":"Paya Dapur"},{"id":"1101142002","district_id":"110114","name":"Sapik"},{"id":"1101142003","district_id":"110114","name":"Alai"},{"id":"1101142004","district_id":"110114","name":"Durian Kawan"},{"id":"1101142005","district_id":"110114","name":"Lawe Sawah"},{"id":"1101142006","district_id":"110114","name":"Lawe Buluh Didi"},{"id":"1101142007","district_id":"110114","name":"Pucuk Lembang"},{"id":"1101142008","district_id":"110114","name":"Paya Laba"},{"id":"1101142009","district_id":"110114","name":"Lawe Cimanok"}]