[{"id":"1205141001","district_id":"120514","name":"Pelawi Utara"},{"id":"1205141006","district_id":"120514","name":"Berandan Barat"},{"id":"1205141007","district_id":"120514","name":"Berandan Timur Baru"},{"id":"1205141008","district_id":"120514","name":"Berandan Timur"},{"id":"1205142002","district_id":"120514","name":"Securai Utara"},{"id":"1205142003","district_id":"120514","name":"Teluk Meku"},{"id":"1205142004","district_id":"120514","name":"Pelawi Selatan"},{"id":"1205142005","district_id":"120514","name":"Securai Selatan"}]