[{"id":"1206052001","district_id":"120605","name":"Partibi Tembe"},{"id":"1206052002","district_id":"120605","name":"Negeri Tongging"},{"id":"1206052003","district_id":"120605","name":"Kodon-Kodon"},{"id":"1206052004","district_id":"120605","name":"Dokan"},{"id":"1206052005","district_id":"120605","name":"Nagara"},{"id":"1206052006","district_id":"120605","name":"Sibolangit"},{"id":"1206052007","district_id":"120605","name":"Sukamandi"},{"id":"1206052008","district_id":"120605","name":"Nagalingga"},{"id":"1206052009","district_id":"120605","name":"Pangambatan"},{"id":"1206052010","district_id":"120605","name":"Tongging"},{"id":"1206052011","district_id":"120605","name":"Partibi Lama"},{"id":"1206052012","district_id":"120605","name":"Regaji"},{"id":"1206052013","district_id":"120605","name":"Ajinembah"},{"id":"1206052014","district_id":"120605","name":"Situnggaling"},{"id":"1206052015","district_id":"120605","name":"Garingging"},{"id":"1206052016","district_id":"120605","name":"Mulia Rayat"},{"id":"1206052017","district_id":"120605","name":"Bandar Tongging"},{"id":"1206052018","district_id":"120605","name":"Pancur Batu"},{"id":"1206052019","district_id":"120605","name":"Merek"}]