[{"id":"1207042001","district_id":"120704","name":"Suka Makmur"},{"id":"1207042002","district_id":"120704","name":"Namo Mirik"},{"id":"1207042003","district_id":"120704","name":"Suka Dame"},{"id":"1207042004","district_id":"120704","name":"Pasar X"},{"id":"1207042005","district_id":"120704","name":"Perpanden"},{"id":"1207042006","district_id":"120704","name":"Kutalimbaru"},{"id":"1207042007","district_id":"120704","name":"Sampe Cita"},{"id":"1207042008","district_id":"120704","name":"Suka Rende"},{"id":"1207042009","district_id":"120704","name":"Kwala Lau Bicik"},{"id":"1207042010","district_id":"120704","name":"Lau Bekeri"},{"id":"1207042011","district_id":"120704","name":"Silebo-Lebo"},{"id":"1207042012","district_id":"120704","name":"Sawit Rejo"},{"id":"1207042013","district_id":"120704","name":"Namo Rube Julu"},{"id":"1207042014","district_id":"120704","name":"Sei Mencirim"}]