[{"id":"1377011001","district_id":"137701","name":"Karan Aur"},{"id":"1377011002","district_id":"137701","name":"Kampung Perak"},{"id":"1377011003","district_id":"137701","name":"Lohong"},{"id":"1377011004","district_id":"137701","name":"Pasir"},{"id":"1377011005","district_id":"137701","name":"Kampung Pondok"},{"id":"1377011006","district_id":"137701","name":"Pondok II"},{"id":"1377011007","district_id":"137701","name":"Kampung Jawa I"},{"id":"1377011008","district_id":"137701","name":"Kampung Jawa II"},{"id":"1377011009","district_id":"137701","name":"Alai Gelombang"},{"id":"1377011010","district_id":"137701","name":"Jawi Jawi I"},{"id":"1377011011","district_id":"137701","name":"Jawi Jawi II"},{"id":"1377011012","district_id":"137701","name":"Jalan Baru"},{"id":"1377011013","district_id":"137701","name":"Taratak"},{"id":"1377011014","district_id":"137701","name":"Jalan Kereta Api"},{"id":"1377011015","district_id":"137701","name":"Ujung Batung"},{"id":"1377011016","district_id":"137701","name":"Jati Hilir"},{"id":"1377012017","district_id":"137701","name":"Pauh Barat"},{"id":"1377012018","district_id":"137701","name":"Pauh Timur"},{"id":"1377012019","district_id":"137701","name":"Rawang"},{"id":"1377012020","district_id":"137701","name":"Kampung Baru"},{"id":"1377012021","district_id":"137701","name":"Cimparuh"},{"id":"1377012025","district_id":"137701","name":"Jati Mudik"}]