[{"id":"1501232001","district_id":"150123","name":"Pancuran Tiga"},{"id":"1501232002","district_id":"150123","name":"Tanjung Pauh Mudik"},{"id":"1501232003","district_id":"150123","name":"Bukit Pulai"},{"id":"1501232004","district_id":"150123","name":"Punai Merindu"},{"id":"1501232005","district_id":"150123","name":"Sumur Jauh"},{"id":"1501232006","district_id":"150123","name":"Permai Baru"},{"id":"1501232007","district_id":"150123","name":"Tanjung Pauh Hilir"},{"id":"1501232008","district_id":"150123","name":"Serumpun Pauh"},{"id":"1501232009","district_id":"150123","name":"Pondok Siguang"},{"id":"1501232010","district_id":"150123","name":"Koto Tengah"},{"id":"1501232011","district_id":"150123","name":"Semerap"},{"id":"1501232012","district_id":"150123","name":"Koto Baru Semerap"},{"id":"1501232013","district_id":"150123","name":"Pasar Semerap"},{"id":"1501232014","district_id":"150123","name":"Koto Patah"}]