[{"id":"1604101031","district_id":"160410","name":"Lahat Tengah"},{"id":"1604101032","district_id":"160410","name":"Gunung Gajah"},{"id":"1604101033","district_id":"160410","name":"Pagar Agung"},{"id":"1604101037","district_id":"160410","name":"Talang Jawa"},{"id":"1604101038","district_id":"160410","name":"Pasar Baru"},{"id":"1604101040","district_id":"160410","name":"Kota Baru"},{"id":"1604101041","district_id":"160410","name":"Pasar Lama"},{"id":"1604101042","district_id":"160410","name":"Pasar Bawah"},{"id":"1604101043","district_id":"160410","name":"Rd Pjka"},{"id":"1604101046","district_id":"160410","name":"Bandar Agung"},{"id":"1604101051","district_id":"160410","name":"Kota Negara"},{"id":"1604101052","district_id":"160410","name":"Kota Jaya"},{"id":"1604101054","district_id":"160410","name":"Rd Pjka Bandar Agung"},{"id":"1604101058","district_id":"160410","name":"Sari Bunga Mas"},{"id":"1604101059","district_id":"160410","name":"Bandar Jaya"},{"id":"1604101060","district_id":"160410","name":"Talang Jawa Selatan"},{"id":"1604101061","district_id":"160410","name":"Talang Jawa Utara"},{"id":"1604102012","district_id":"160410","name":"Padang Lengkuas"},{"id":"1604102027","district_id":"160410","name":"Selawi"},{"id":"1604102030","district_id":"160410","name":"Sukanegara"},{"id":"1604102034","district_id":"160410","name":"Kota Raya"},{"id":"1604102035","district_id":"160410","name":"Keban"},{"id":"1604102036","district_id":"160410","name":"Pagar Sari"},{"id":"1604102039","district_id":"160410","name":"Pagar Negara"},{"id":"1604102049","district_id":"160410","name":"Senabing"},{"id":"1604102050","district_id":"160410","name":"Manggul"},{"id":"1604102053","district_id":"160410","name":"Ulak Lebar"},{"id":"1604102055","district_id":"160410","name":"Giri Mulya"},{"id":"1604102056","district_id":"160410","name":"Makarti Tama"},{"id":"1604102057","district_id":"160410","name":"Ulak Mas"}]