[{"id":"1609072001","district_id":"160907","name":"Sugih Rawas"},{"id":"1609072002","district_id":"160907","name":"Padang Sari"},{"id":"1609072003","district_id":"160907","name":"Padang Bindu"},{"id":"1609072005","district_id":"160907","name":"Saung Naga"},{"id":"1609072006","district_id":"160907","name":"Negeri Batin Baru"},{"id":"1609072007","district_id":"160907","name":"Kota Aman"},{"id":"1609072008","district_id":"160907","name":"Belambangan"},{"id":"1609072009","district_id":"160907","name":"Paninjauan"},{"id":"1609072018","district_id":"160907","name":"Nagar Agung"},{"id":"1609072019","district_id":"160907","name":"Simpang Saga"},{"id":"1609072020","district_id":"160907","name":"Perupus Blambangan"},{"id":"1609072021","district_id":"160907","name":"Kagelang Blambangan"},{"id":"1609072022","district_id":"160907","name":"Sukajadi Blambangan"},{"id":"1609072023","district_id":"160907","name":"Bedeng Blambangan"}]