[{"id":"1704012001","district_id":"170401","name":"Gedung Wani"},{"id":"1704012002","district_id":"170401","name":"Penandingan"},{"id":"1704012003","district_id":"170401","name":"Geramat"},{"id":"1704012004","district_id":"170401","name":"Tanjung Alam"},{"id":"1704012005","district_id":"170401","name":"Tanjung Baru"},{"id":"1704012006","district_id":"170401","name":"Pengurung"},{"id":"1704012007","district_id":"170401","name":"Pinang Jawa"},{"id":"1704012008","district_id":"170401","name":"Gunung Terang"},{"id":"1704012009","district_id":"170401","name":"Talang Padang"},{"id":"1704012010","district_id":"170401","name":"Gunung Megang"},{"id":"1704012020","district_id":"170401","name":"Talang Berangin"},{"id":"1704012021","district_id":"170401","name":"Jawi"},{"id":"1704012022","district_id":"170401","name":"Papahan"},{"id":"1704012023","district_id":"170401","name":"Pinang Jawa II"}]