[{"id":"1709022001","district_id":"170902","name":"Air Sebakul"},{"id":"1709022004","district_id":"170902","name":"Taba Pasmah"},{"id":"1709022005","district_id":"170902","name":"Kembang Seri"},{"id":"1709022006","district_id":"170902","name":"Tengah Padang"},{"id":"1709022007","district_id":"170902","name":"Jayakarta"},{"id":"1709022008","district_id":"170902","name":"Nakau"},{"id":"1709022009","district_id":"170902","name":"Pulau Panggung"},{"id":"1709022014","district_id":"170902","name":"Jum'at"},{"id":"1709022015","district_id":"170902","name":"Padang Ulak Tanjung"},{"id":"1709022017","district_id":"170902","name":"Air Putih"}]