[{"id":"3201062001","district_id":"320106","name":"Sukamaju"},{"id":"3201062002","district_id":"320106","name":"Sirnagalih"},{"id":"3201062003","district_id":"320106","name":"Singajaya"},{"id":"3201062004","district_id":"320106","name":"Sukasirna"},{"id":"3201062005","district_id":"320106","name":"Sukanegara"},{"id":"3201062006","district_id":"320106","name":"Sukamanah"},{"id":"3201062007","district_id":"320106","name":"Weninggalih"},{"id":"3201062008","district_id":"320106","name":"Cibodas"},{"id":"3201062009","district_id":"320106","name":"Jonggol"},{"id":"3201062010","district_id":"320106","name":"Bendungan"},{"id":"3201062011","district_id":"320106","name":"Singasari"},{"id":"3201062012","district_id":"320106","name":"Balekambang"},{"id":"3201062013","district_id":"320106","name":"Sukajaya"},{"id":"3201062014","district_id":"320106","name":"Sukagalih"}]