[{"id":"3202211001","district_id":"320221","name":"Jampangkulon"},{"id":"3202212002","district_id":"320221","name":"Bojonggenteng"},{"id":"3202212003","district_id":"320221","name":"Cikarang"},{"id":"3202212005","district_id":"320221","name":"Bojongsari"},{"id":"3202212007","district_id":"320221","name":"Nagraksari"},{"id":"3202212008","district_id":"320221","name":"Mekarjaya"},{"id":"3202212009","district_id":"320221","name":"Tanjung"},{"id":"3202212011","district_id":"320221","name":"Ciparay"},{"id":"3202212013","district_id":"320221","name":"Padajaya"},{"id":"3202212014","district_id":"320221","name":"Karanganyar"},{"id":"3202212016","district_id":"320221","name":"Cikaranggeusan"}]