[{"id":"3209112001","district_id":"320911","name":"Getrakmoyan"},{"id":"3209112002","district_id":"320911","name":"Ender"},{"id":"3209112003","district_id":"320911","name":"Pangenan"},{"id":"3209112004","district_id":"320911","name":"Bendungan"},{"id":"3209112005","district_id":"320911","name":"Rawaurip"},{"id":"3209112006","district_id":"320911","name":"Beringin"},{"id":"3209112007","district_id":"320911","name":"Japura Lor"},{"id":"3209112008","district_id":"320911","name":"Pengarengan"},{"id":"3209112009","district_id":"320911","name":"Astanamukti"}]