[{"id":"3323091019","district_id":"332309","name":"Manggong"},{"id":"3323092001","district_id":"332309","name":"Ngadirejo"},{"id":"3323092002","district_id":"332309","name":"Gondangwinangun"},{"id":"3323092003","district_id":"332309","name":"Gandu Wetan"},{"id":"3323092004","district_id":"332309","name":"Ngaren"},{"id":"3323092005","district_id":"332309","name":"Mangunsari"},{"id":"3323092006","district_id":"332309","name":"Dlimoyo"},{"id":"3323092007","district_id":"332309","name":"Purbosari"},{"id":"3323092008","district_id":"332309","name":"Campursari"},{"id":"3323092009","district_id":"332309","name":"Tegalrejo"},{"id":"3323092010","district_id":"332309","name":"Giripurno"},{"id":"3323092011","district_id":"332309","name":"Katekan"},{"id":"3323092012","district_id":"332309","name":"Banjarsari"},{"id":"3323092013","district_id":"332309","name":"Medari"},{"id":"3323092014","district_id":"332309","name":"Karanggedong"},{"id":"3323092015","district_id":"332309","name":"Munggangsari"},{"id":"3323092016","district_id":"332309","name":"Kataan"},{"id":"3323092017","district_id":"332309","name":"Petirejo"},{"id":"3323092018","district_id":"332309","name":"Pringapus"},{"id":"3323092020","district_id":"332309","name":"Gejagan"}]