[{"id":"3502022001","district_id":"350202","name":"Wonodadi"},{"id":"3502022002","district_id":"350202","name":"Sendang"},{"id":"3502022003","district_id":"350202","name":"Baosan Kidul"},{"id":"3502022004","district_id":"350202","name":"Binade"},{"id":"3502022005","district_id":"350202","name":"Mrayan"},{"id":"3502022006","district_id":"350202","name":"Baosan Lor"},{"id":"3502022007","district_id":"350202","name":"Temon"},{"id":"3502022008","district_id":"350202","name":"Selur"},{"id":"3502022009","district_id":"350202","name":"Ngrayun"},{"id":"3502022010","district_id":"350202","name":"Cepoko"},{"id":"3502022011","district_id":"350202","name":"Gedangan"}]