[{"id":"3516122001","district_id":"351612","name":"Jambuwok"},{"id":"3516122002","district_id":"351612","name":"Domas"},{"id":"3516122003","district_id":"351612","name":"Beloh"},{"id":"3516122004","district_id":"351612","name":"Temon"},{"id":"3516122005","district_id":"351612","name":"Pakis"},{"id":"3516122006","district_id":"351612","name":"Sentonorejo"},{"id":"3516122007","district_id":"351612","name":"Trowulan"},{"id":"3516122008","district_id":"351612","name":"Bejijong"},{"id":"3516122009","district_id":"351612","name":"Kejagan"},{"id":"3516122010","district_id":"351612","name":"Jatipasar"},{"id":"3516122011","district_id":"351612","name":"Watesumpak"},{"id":"3516122012","district_id":"351612","name":"Wonorejo"},{"id":"3516122013","district_id":"351612","name":"Panggih"},{"id":"3516122014","district_id":"351612","name":"Tawangsari"},{"id":"3516122015","district_id":"351612","name":"Bicak"},{"id":"3516122016","district_id":"351612","name":"Balongwono"}]