[{"id":"3524092001","district_id":"352409","name":"Besur"},{"id":"3524092002","district_id":"352409","name":"Titik"},{"id":"3524092003","district_id":"352409","name":"Kendal"},{"id":"3524092004","district_id":"352409","name":"Keting"},{"id":"3524092005","district_id":"352409","name":"Ngarum"},{"id":"3524092006","district_id":"352409","name":"Kebalankulon"},{"id":"3524092007","district_id":"352409","name":"Kudikan"},{"id":"3524092008","district_id":"352409","name":"Jugo"},{"id":"3524092009","district_id":"352409","name":"Manyar"},{"id":"3524092010","district_id":"352409","name":"Trosono"},{"id":"3524092011","district_id":"352409","name":"Latek"},{"id":"3524092012","district_id":"352409","name":"Miru"},{"id":"3524092013","district_id":"352409","name":"Sekaran"},{"id":"3524092014","district_id":"352409","name":"Moro"},{"id":"3524092015","district_id":"352409","name":"Karang"},{"id":"3524092016","district_id":"352409","name":"Kembangan"},{"id":"3524092017","district_id":"352409","name":"Siman"},{"id":"3524092018","district_id":"352409","name":"Bulutengger"},{"id":"3524092019","district_id":"352409","name":"Porodeso"},{"id":"3524092020","district_id":"352409","name":"Bugel"},{"id":"3524092021","district_id":"352409","name":"Sungegeneng"}]