[{"id":"3603121005","district_id":"360312","name":"Sindangsari"},{"id":"3603121010","district_id":"360312","name":"Kutabumi"},{"id":"3603121012","district_id":"360312","name":"Kuta Jaya"},{"id":"3603121014","district_id":"360312","name":"Kuta Baru"},{"id":"3603122001","district_id":"360312","name":"Pasar Kemis"},{"id":"3603122008","district_id":"360312","name":"Sukamantri"},{"id":"3603122011","district_id":"360312","name":"Pangadegan"},{"id":"3603122013","district_id":"360312","name":"Gelam Jaya"},{"id":"3603122015","district_id":"360312","name":"Suka Asih"}]