[{"id":"5108032001","district_id":"510803","name":"Sepang"},{"id":"5108032002","district_id":"510803","name":"Dapdap Putih"},{"id":"5108032003","district_id":"510803","name":"Bongancina"},{"id":"5108032004","district_id":"510803","name":"Pucaksari"},{"id":"5108032005","district_id":"510803","name":"Telaga"},{"id":"5108032006","district_id":"510803","name":"Titab"},{"id":"5108032007","district_id":"510803","name":"Subuk"},{"id":"5108032008","district_id":"510803","name":"Tinggarsari"},{"id":"5108032009","district_id":"510803","name":"Kedis"},{"id":"5108032010","district_id":"510803","name":"Kekeran"},{"id":"5108032011","district_id":"510803","name":"Busungbiu"},{"id":"5108032012","district_id":"510803","name":"Pelapuan"},{"id":"5108032013","district_id":"510803","name":"Bengkel"},{"id":"5108032014","district_id":"510803","name":"Umejero"},{"id":"5108032015","district_id":"510803","name":"Sepang Kelod"}]