[{"id":"5301111007","district_id":"530111","name":"Takari"},{"id":"5301112001","district_id":"530111","name":"Noelmina"},{"id":"5301112002","district_id":"530111","name":"Benu"},{"id":"5301112003","district_id":"530111","name":"Hueknutu"},{"id":"5301112004","district_id":"530111","name":"Oelnaineno"},{"id":"5301112005","district_id":"530111","name":"Tanini"},{"id":"5301112006","district_id":"530111","name":"Kauniki"},{"id":"5301112008","district_id":"530111","name":"Tuapanaf"},{"id":"5301112009","district_id":"530111","name":"Fatukona"},{"id":"5301112010","district_id":"530111","name":"Oesusu"}]