[{"id":"5302132001","district_id":"530213","name":"Konbaki"},{"id":"5302132002","district_id":"530213","name":"Fatumnutu"},{"id":"5302132003","district_id":"530213","name":"Bijeli"},{"id":"5302132004","district_id":"530213","name":"Loli"},{"id":"5302132005","district_id":"530213","name":"Usapimnasi"},{"id":"5302132006","district_id":"530213","name":"Mnesatbubuk"},{"id":"5302132007","district_id":"530213","name":"Puna"},{"id":"5302132008","district_id":"530213","name":"Laob"},{"id":"5302132009","district_id":"530213","name":"Oelnunuh"},{"id":"5302132010","district_id":"530213","name":"Balu"},{"id":"5302132011","district_id":"530213","name":"Sainoni"}]