[{"id":"6106112001","district_id":"610611","name":"Sejiram"},{"id":"6106112002","district_id":"610611","name":"Beluis Harum"},{"id":"6106112003","district_id":"610611","name":"Gurung"},{"id":"6106112004","district_id":"610611","name":"Bati"},{"id":"6106112005","district_id":"610611","name":"Seneban"},{"id":"6106112006","district_id":"610611","name":"Belikai"},{"id":"6106112007","district_id":"610611","name":"Ranyai"},{"id":"6106112008","district_id":"610611","name":"Emperiang"},{"id":"6106112009","district_id":"610611","name":"Pala Kota"},{"id":"6106112010","district_id":"610611","name":"Nanga Lot"},{"id":"6106112011","district_id":"610611","name":"Tanjung Keliling"},{"id":"6106112012","district_id":"610611","name":"Tajau Mada"},{"id":"6106112013","district_id":"610611","name":"Jerenjang"},{"id":"6106112014","district_id":"610611","name":"Bekuan"},{"id":"6106112015","district_id":"610611","name":"Nanga Pala"}]