[{"id":"7301082001","district_id":"730108","name":"Kayuadi"},{"id":"7301082002","district_id":"730108","name":"Batang"},{"id":"7301082003","district_id":"730108","name":"Nyiur Indah"},{"id":"7301082004","district_id":"730108","name":"Tambuna"},{"id":"7301082005","district_id":"730108","name":"Jinato"},{"id":"7301082006","district_id":"730108","name":"Rajuni"},{"id":"7301082007","district_id":"730108","name":"Latondu"},{"id":"7301082008","district_id":"730108","name":"Tarupa"},{"id":"7301082009","district_id":"730108","name":"Khusus Pasitallu"}]