[{"id":"8105072001","district_id":"810507","name":"Dihil"},{"id":"8105072002","district_id":"810507","name":"Liliama"},{"id":"8105072003","district_id":"810507","name":"Naiwel Ahinulin"},{"id":"8105072004","district_id":"810507","name":"Polin"},{"id":"8105072005","district_id":"810507","name":"Tunsai"},{"id":"8105072006","district_id":"810507","name":"Lapela"},{"id":"8105072007","district_id":"810507","name":"Nayet"},{"id":"8105072008","district_id":"810507","name":"Elnusa"},{"id":"8105072009","district_id":"810507","name":"Atiahu"},{"id":"8105072010","district_id":"810507","name":"Sabuai"},{"id":"8105072011","district_id":"810507","name":"Abulate"},{"id":"8105072012","district_id":"810507","name":"Adabai"}]