[{"id":"9601011001","district_id":"960101","name":"Makbon"},{"id":"9601012002","district_id":"960101","name":"Asbaken"},{"id":"9601012003","district_id":"960101","name":"Malaumkarta"},{"id":"9601012004","district_id":"960101","name":"Batu Lubang"},{"id":"9601012005","district_id":"960101","name":"Batu Lubang Pantai"},{"id":"9601012006","district_id":"960101","name":"Kwadas"},{"id":"9601012007","district_id":"960101","name":"Bainkete"},{"id":"9601012008","district_id":"960101","name":"Teluk Dore"},{"id":"9601012009","district_id":"960101","name":"Sawatuk"},{"id":"9601012010","district_id":"960101","name":"Malagasih"},{"id":"9601012011","district_id":"960101","name":"Klasimigik"},{"id":"9601012012","district_id":"960101","name":"Klasigi"},{"id":"9601012013","district_id":"960101","name":"Klagulus"},{"id":"9601012014","district_id":"960101","name":"Suatolo"},{"id":"9601012015","district_id":"960101","name":"Mibi"}]