[{"id":"9501","province_id":"95","name":"Kabupaten Jayawijaya"},{"id":"9502","province_id":"95","name":"Kabupaten Pegunungan Bintang"},{"id":"9503","province_id":"95","name":"Kabupaten Yahukimo"},{"id":"9504","province_id":"95","name":"Kabupaten Tolikara"},{"id":"9505","province_id":"95","name":"Kabupaten Mamberamo Tengah"},{"id":"9506","province_id":"95","name":"Kabupaten Yalimo"},{"id":"9507","province_id":"95","name":"Kabupaten Lanny Jaya"},{"id":"9508","province_id":"95","name":"Kabupaten Nduga"}]