[{"id":"131001","regency_id":"1310","name":"Koto Baru"},{"id":"131002","regency_id":"1310","name":"Pulau Punjung"},{"id":"131003","regency_id":"1310","name":"Sungai Rumbai"},{"id":"131004","regency_id":"1310","name":"Sitiung"},{"id":"131005","regency_id":"1310","name":"Sembilan Koto"},{"id":"131006","regency_id":"1310","name":"Timpeh"},{"id":"131007","regency_id":"1310","name":"Koto Salak"},{"id":"131008","regency_id":"1310","name":"Tiumang"},{"id":"131009","regency_id":"1310","name":"Padang Laweh"},{"id":"131010","regency_id":"1310","name":"Asam Jujuhan"},{"id":"131011","regency_id":"1310","name":"Koto Besar"}]