[{"id":"731801","regency_id":"7318","name":"Salupputti"},{"id":"731802","regency_id":"7318","name":"Bittuang"},{"id":"731803","regency_id":"7318","name":"Bonggakaradeng"},{"id":"731805","regency_id":"7318","name":"Makale"},{"id":"731809","regency_id":"7318","name":"Simbuang"},{"id":"731811","regency_id":"7318","name":"Rantetayo"},{"id":"731812","regency_id":"7318","name":"Mengkendek"},{"id":"731813","regency_id":"7318","name":"Sangalla'"},{"id":"731819","regency_id":"7318","name":"Gandangbatu Sillanan"},{"id":"731820","regency_id":"7318","name":"Rembon"},{"id":"731827","regency_id":"7318","name":"Makale Utara"},{"id":"731828","regency_id":"7318","name":"Mappak"},{"id":"731829","regency_id":"7318","name":"Makale Selatan"},{"id":"731831","regency_id":"7318","name":"Masanda"},{"id":"731833","regency_id":"7318","name":"Sangalla' Selatan"},{"id":"731834","regency_id":"7318","name":"Sangalla' Utara"},{"id":"731835","regency_id":"7318","name":"Malimbong Balepe'"},{"id":"731837","regency_id":"7318","name":"Rano"},{"id":"731838","regency_id":"7318","name":"Kurra"}]