[{"id":"1214082001","district_id":"121408","name":"Amuri"},{"id":"1214082004","district_id":"121408","name":"Bawosalo'o Siwalawa"},{"id":"1214082009","district_id":"121408","name":"Hilifadolo"},{"id":"1214082014","district_id":"121408","name":"Lolofaoso"},{"id":"1214082015","district_id":"121408","name":"Lolomoyo"},{"id":"1214082016","district_id":"121408","name":"Lolowau"},{"id":"1214082017","district_id":"121408","name":"Lolohowa"},{"id":"1214082022","district_id":"121408","name":"Sisarahili Ekholo"},{"id":"1214082030","district_id":"121408","name":"Tuhegafoa"},{"id":"1214082033","district_id":"121408","name":"Botohili"},{"id":"1214082035","district_id":"121408","name":"Hilikara"},{"id":"1214082044","district_id":"121408","name":"Samiri"},{"id":"1214082047","district_id":"121408","name":"Hilimbowo Siwalawa"},{"id":"1214082048","district_id":"121408","name":"Nituwu Boho"}]