[{"id":"1406092001","district_id":"140609","name":"Tambusai Utara"},{"id":"1406092002","district_id":"140609","name":"Mahato"},{"id":"1406092003","district_id":"140609","name":"Bangun Jaya"},{"id":"1406092004","district_id":"140609","name":"Simpang Harapan"},{"id":"1406092005","district_id":"140609","name":"Pagar Mayang"},{"id":"1406092006","district_id":"140609","name":"Payung Sekaki"},{"id":"1406092007","district_id":"140609","name":"Mekar Jaya"},{"id":"1406092008","district_id":"140609","name":"Tanjung Medan"},{"id":"1406092009","district_id":"140609","name":"Suka Damai"},{"id":"1406092010","district_id":"140609","name":"Rantau Sakti"},{"id":"1406092011","district_id":"140609","name":"Mahato Sakti"}]