[{"id":"1606152001","district_id":"160615","name":"Jirak"},{"id":"1606152002","district_id":"160615","name":"Rukun Rahayu"},{"id":"1606152003","district_id":"160615","name":"Talang Simpang"},{"id":"1606152004","district_id":"160615","name":"Jembatan Gantung"},{"id":"1606152005","district_id":"160615","name":"Talang Mandung"},{"id":"1606152006","district_id":"160615","name":"Rejosari"},{"id":"1606152007","district_id":"160615","name":"Bangkit Jaya"},{"id":"1606152008","district_id":"160615","name":"Baru Jaya"},{"id":"1606152009","district_id":"160615","name":"Sinar Jaya"},{"id":"1606152010","district_id":"160615","name":"Setia Jaya"},{"id":"1606152011","district_id":"160615","name":"Mekar Jaya"},{"id":"1606152012","district_id":"160615","name":"Layan"}]