[{"id":"1802012001","district_id":"180201","name":"Sri Way Langsep"},{"id":"1802012002","district_id":"180201","name":"Wayakrui"},{"id":"1802012003","district_id":"180201","name":"Kalirejo"},{"id":"1802012004","district_id":"180201","name":"Balai Rejo"},{"id":"1802012005","district_id":"180201","name":"Watu Agung"},{"id":"1802012006","district_id":"180201","name":"Sri Basuki"},{"id":"1802012007","district_id":"180201","name":"Kaliwungu"},{"id":"1802012008","district_id":"180201","name":"Kali Dadi"},{"id":"1802012009","district_id":"180201","name":"Sri Mulyo"},{"id":"1802012010","district_id":"180201","name":"Sri Dadi"},{"id":"1802012011","district_id":"180201","name":"Suko Sari"},{"id":"1802012012","district_id":"180201","name":"Sinar Sari"},{"id":"1802012013","district_id":"180201","name":"Ponco Warno"},{"id":"1802012014","district_id":"180201","name":"Sri Purnomo"},{"id":"1802012015","district_id":"180201","name":"Sinar Rejo"},{"id":"1802012016","district_id":"180201","name":"Agung Timur"},{"id":"1802012017","district_id":"180201","name":"Kalisari"}]