[{"id":"1803212001","district_id":"180321","name":"Sinar Harapan"},{"id":"1803212002","district_id":"180321","name":"Kubu Hitu"},{"id":"1803212003","district_id":"180321","name":"Negeri Sakti"},{"id":"1803212004","district_id":"180321","name":"Tanjung Jaya"},{"id":"1803212005","district_id":"180321","name":"Gunung Raja"},{"id":"1803212006","district_id":"180321","name":"Cahaya Mas"},{"id":"1803212007","district_id":"180321","name":"Comok Sinar Jaya"},{"id":"1803212008","district_id":"180321","name":"Way Isem"},{"id":"1803212009","district_id":"180321","name":"Gunung Maknibai"},{"id":"1803212010","district_id":"180321","name":"Negeri Batin Jaya"}]