[{"id":"3203082001","district_id":"320308","name":"Kademangan"},{"id":"3203082002","district_id":"320308","name":"Bobojong"},{"id":"3203082003","district_id":"320308","name":"Jamali"},{"id":"3203082004","district_id":"320308","name":"Cikidangbayabang"},{"id":"3203082005","district_id":"320308","name":"Mande"},{"id":"3203082006","district_id":"320308","name":"Mulyasari"},{"id":"3203082007","district_id":"320308","name":"Ciandam"},{"id":"3203082008","district_id":"320308","name":"Sukamanah"},{"id":"3203082009","district_id":"320308","name":"Leuwikoja"},{"id":"3203082010","district_id":"320308","name":"Mekarjaya"},{"id":"3203082011","district_id":"320308","name":"Kutawaringin"},{"id":"3203082012","district_id":"320308","name":"Murnisari"}]