[{"id":"3210052001","district_id":"321005","name":"Sagara"},{"id":"3210052002","district_id":"321005","name":"Cibunut"},{"id":"3210052003","district_id":"321005","name":"Tejamulya"},{"id":"3210052004","district_id":"321005","name":"Sukasari Kaler"},{"id":"3210052005","district_id":"321005","name":"Argamukti"},{"id":"3210052006","district_id":"321005","name":"Sukadana"},{"id":"3210052007","district_id":"321005","name":"Sadasari"},{"id":"3210052008","district_id":"321005","name":"Haurseah"},{"id":"3210052009","district_id":"321005","name":"Mekarwangi"},{"id":"3210052010","district_id":"321005","name":"Cikaracak"},{"id":"3210052011","district_id":"321005","name":"Heubeulisuk"},{"id":"3210052012","district_id":"321005","name":"Sukasari Kidul"},{"id":"3210052013","district_id":"321005","name":"Gunungwangi"},{"id":"3210052014","district_id":"321005","name":"Argalingga"}]