[{"id":"3211242001","district_id":"321124","name":"Tomo"},{"id":"3211242002","district_id":"321124","name":"Tolengas"},{"id":"3211242003","district_id":"321124","name":"Darmawangi"},{"id":"3211242004","district_id":"321124","name":"Marongge"},{"id":"3211242005","district_id":"321124","name":"Jembarwangi"},{"id":"3211242006","district_id":"321124","name":"Bugel"},{"id":"3211242007","district_id":"321124","name":"Cipeles"},{"id":"3211242008","district_id":"321124","name":"Karyamukti"},{"id":"3211242010","district_id":"321124","name":"Mekarwangi"}]