[{"id":"3504142001","district_id":"350414","name":"Kalibatur"},{"id":"3504142002","district_id":"350414","name":"Rejosari"},{"id":"3504142003","district_id":"350414","name":"Sukorejo Kulon"},{"id":"3504142004","district_id":"350414","name":"Kalidawir"},{"id":"3504142005","district_id":"350414","name":"Karangtalun"},{"id":"3504142006","district_id":"350414","name":"Banyuurip"},{"id":"3504142007","district_id":"350414","name":"Winong"},{"id":"3504142008","district_id":"350414","name":"Joho"},{"id":"3504142009","district_id":"350414","name":"Pakisaji"},{"id":"3504142010","district_id":"350414","name":"Jabon"},{"id":"3504142011","district_id":"350414","name":"Tunggangri"},{"id":"3504142012","district_id":"350414","name":"Salakkembang"},{"id":"3504142013","district_id":"350414","name":"Ngubalan"},{"id":"3504142014","district_id":"350414","name":"Domasan"},{"id":"3504142015","district_id":"350414","name":"Tanjung"},{"id":"3504142016","district_id":"350414","name":"Betak"},{"id":"3504142017","district_id":"350414","name":"Pagersari"}]