[{"id":"3509182001","district_id":"350918","name":"Sidodadi"},{"id":"3509182002","district_id":"350918","name":"Tempurejo"},{"id":"3509182003","district_id":"350918","name":"Andongrejo"},{"id":"3509182004","district_id":"350918","name":"Pondokrejo"},{"id":"3509182005","district_id":"350918","name":"Wonoasri"},{"id":"3509182006","district_id":"350918","name":"Curahnongko"},{"id":"3509182007","district_id":"350918","name":"Curahtakir"},{"id":"3509182008","district_id":"350918","name":"Sanenrejo"}]