[{"id":"3514131013","district_id":"351413","name":"Glanggang"},{"id":"3514131014","district_id":"351413","name":"Pagak"},{"id":"3514132001","district_id":"351413","name":"Baujeng"},{"id":"3514132002","district_id":"351413","name":"Ngembe"},{"id":"3514132003","district_id":"351413","name":"Kenep"},{"id":"3514132004","district_id":"351413","name":"Sidowayah"},{"id":"3514132005","district_id":"351413","name":"Gajahbendo"},{"id":"3514132006","district_id":"351413","name":"Gununggangsir"},{"id":"3514132007","district_id":"351413","name":"Wonokoyo"},{"id":"3514132008","district_id":"351413","name":"Gunungsari"},{"id":"3514132009","district_id":"351413","name":"Cangkringmalang"},{"id":"3514132010","district_id":"351413","name":"Kedungringin"},{"id":"3514132011","district_id":"351413","name":"Kedungboto"},{"id":"3514132012","district_id":"351413","name":"Beji"}]