[{"id":"3571031001","district_id":"357103","name":"Bangsal"},{"id":"3571031002","district_id":"357103","name":"Pakunden"},{"id":"3571031003","district_id":"357103","name":"Tosaren"},{"id":"3571031004","district_id":"357103","name":"Jamsaren"},{"id":"3571031005","district_id":"357103","name":"Singonegaran"},{"id":"3571031006","district_id":"357103","name":"Blabak"},{"id":"3571031007","district_id":"357103","name":"Betet"},{"id":"3571031008","district_id":"357103","name":"Tinalan"},{"id":"3571031009","district_id":"357103","name":"Bawang"},{"id":"3571031010","district_id":"357103","name":"Ngletih"},{"id":"3571031011","district_id":"357103","name":"Tempurejo"},{"id":"3571031012","district_id":"357103","name":"Ketami"},{"id":"3571031013","district_id":"357103","name":"Pesantren"},{"id":"3571031014","district_id":"357103","name":"Banaran"},{"id":"3571031015","district_id":"357103","name":"Burengan"}]