[{"id":"3571021001","district_id":"357102","name":"Semampir"},{"id":"3571021002","district_id":"357102","name":"Balowerti"},{"id":"3571021003","district_id":"357102","name":"Dandangan"},{"id":"3571021004","district_id":"357102","name":"Ngadirejo"},{"id":"3571021005","district_id":"357102","name":"Kampung Dalem"},{"id":"3571021006","district_id":"357102","name":"Setonopande"},{"id":"3571021007","district_id":"357102","name":"Ringinanom"},{"id":"3571021008","district_id":"357102","name":"Pakelan"},{"id":"3571021009","district_id":"357102","name":"Setonogedong"},{"id":"3571021010","district_id":"357102","name":"Kemasan"},{"id":"3571021011","district_id":"357102","name":"Jagalan"},{"id":"3571021012","district_id":"357102","name":"Banjaran"},{"id":"3571021013","district_id":"357102","name":"Kaliombo"},{"id":"3571021014","district_id":"357102","name":"Ngronggo"},{"id":"3571021015","district_id":"357102","name":"Manisrenggo"},{"id":"3571021016","district_id":"357102","name":"Pocanan"},{"id":"3571021017","district_id":"357102","name":"Rejomulyo"}]