[{"id":"5306182001","district_id":"530618","name":"Horowura"},{"id":"5306182002","district_id":"530618","name":"Kokotobo"},{"id":"5306182003","district_id":"530618","name":"Lite"},{"id":"5306182004","district_id":"530618","name":"Kenotan"},{"id":"5306182005","district_id":"530618","name":"Nubalema"},{"id":"5306182006","district_id":"530618","name":"Wewit"},{"id":"5306182007","district_id":"530618","name":"Lewobele"},{"id":"5306182008","district_id":"530618","name":"Baya"},{"id":"5306182009","district_id":"530618","name":"Bidara"},{"id":"5306182010","district_id":"530618","name":"Oesayang"},{"id":"5306182011","district_id":"530618","name":"Hoko Horowura"},{"id":"5306182012","district_id":"530618","name":"Lewopao"},{"id":"5306182013","district_id":"530618","name":"Nubalema Dua"}]