[{"id":"6209052001","district_id":"620905","name":"Melata"},{"id":"6209052002","district_id":"620905","name":"Nanuah"},{"id":"6209052003","district_id":"620905","name":"Batu Ampar"},{"id":"6209052004","district_id":"620905","name":"Lubuk Hiju"},{"id":"6209052005","district_id":"620905","name":"Topalan"},{"id":"6209052006","district_id":"620905","name":"Bukit Makmur"},{"id":"6209052007","district_id":"620905","name":"Modang Mas"},{"id":"6209052008","district_id":"620905","name":"Bukit Raya"},{"id":"6209052009","district_id":"620905","name":"Mukti Manunggal"},{"id":"6209052010","district_id":"620905","name":"Sumber Jaya"},{"id":"6209052011","district_id":"620905","name":"Bukit Harum"}]