[{"id":"7108012001","district_id":"710801","name":"Sangkub I"},{"id":"7108012002","district_id":"710801","name":"Busisingo"},{"id":"7108012003","district_id":"710801","name":"Sang Tombolang"},{"id":"7108012004","district_id":"710801","name":"Tombolango"},{"id":"7108012005","district_id":"710801","name":"Pangkusa"},{"id":"7108012006","district_id":"710801","name":"Sangkub II"},{"id":"7108012007","district_id":"710801","name":"Sidodadi"},{"id":"7108012008","district_id":"710801","name":"Sampiro"},{"id":"7108012009","district_id":"710801","name":"Sangkub III"},{"id":"7108012010","district_id":"710801","name":"Busisingo Utara"},{"id":"7108012011","district_id":"710801","name":"Ampeng Sembeka"},{"id":"7108012012","district_id":"710801","name":"Suka Makmur"},{"id":"7108012013","district_id":"710801","name":"Sangkub Timur"},{"id":"7108012014","district_id":"710801","name":"Monompia"},{"id":"7108012015","district_id":"710801","name":"Mokusato"},{"id":"7108012016","district_id":"710801","name":"Sangkub Empat"}]