[{"id":"7109042001","district_id":"710904","name":"Mala"},{"id":"7109042002","district_id":"710904","name":"Pangirolong"},{"id":"7109042003","district_id":"710904","name":"Sawang"},{"id":"7109042004","district_id":"710904","name":"Bandil"},{"id":"7109042005","district_id":"710904","name":"Biau"},{"id":"7109042006","district_id":"710904","name":"Balirangeng"},{"id":"7109042007","district_id":"710904","name":"Buhias"},{"id":"7109042008","district_id":"710904","name":"Tapile"},{"id":"7109042009","district_id":"710904","name":"Lahopang"},{"id":"7109042010","district_id":"710904","name":"Binalu"},{"id":"7109042011","district_id":"710904","name":"Kalihiang"},{"id":"7109042012","district_id":"710904","name":"Pahepa"},{"id":"7109042013","district_id":"710904","name":"Biau Seha"},{"id":"7109042014","district_id":"710904","name":"Matole"}]