[{"id":"7308122001","district_id":"730812","name":"Mattampawalie"},{"id":"7308122002","district_id":"730812","name":"Lili Riattang"},{"id":"7308122003","district_id":"730812","name":"Sengeng Palie"},{"id":"7308122004","district_id":"730812","name":"Tenri Pakkua"},{"id":"7308122005","district_id":"730812","name":"Patangkai"},{"id":"7308122006","district_id":"730812","name":"Ujung Lamuru"},{"id":"7308122007","district_id":"730812","name":"Pattuku Limpoe"},{"id":"7308122008","district_id":"730812","name":"Waekeccee"},{"id":"7308122009","district_id":"730812","name":"Tonronge"}]