[{"id":"7371141001","district_id":"737114","name":"Tamalanrea"},{"id":"7371141002","district_id":"737114","name":"Kapasa"},{"id":"7371141003","district_id":"737114","name":"Tamalanrea Indah"},{"id":"7371141004","district_id":"737114","name":"Parang Loe"},{"id":"7371141005","district_id":"737114","name":"Bira"},{"id":"7371141006","district_id":"737114","name":"Tamalanrea Jaya"},{"id":"7371141007","district_id":"737114","name":"Buntusu"},{"id":"7371141008","district_id":"737114","name":"Kapasa Raya"}]