[{"id":"9103052001","district_id":"910305","name":"Sama"},{"id":"9103052002","district_id":"910305","name":"Manda Yawan"},{"id":"9103052003","district_id":"910305","name":"Mamda"},{"id":"9103052004","district_id":"910305","name":"Mamei"},{"id":"9103052005","district_id":"910305","name":"Nambom"},{"id":"9103052006","district_id":"910305","name":"Kwansu"},{"id":"9103052007","district_id":"910305","name":"Soaib"},{"id":"9103052008","district_id":"910305","name":"Sabeab Kecil"},{"id":"9103052009","district_id":"910305","name":"Sekori"},{"id":"9103052010","district_id":"910305","name":"Skoaim"},{"id":"9103052011","district_id":"910305","name":"Benggwin Progo"},{"id":"9103052012","district_id":"910305","name":"Aib"}]