[{"id":"9403021001","district_id":"940302","name":"Obano"},{"id":"9403022002","district_id":"940302","name":"Kegouda"},{"id":"9403022003","district_id":"940302","name":"Totiyo"},{"id":"9403022004","district_id":"940302","name":"Beko"},{"id":"9403022005","district_id":"940302","name":"Tipakotu"},{"id":"9403022006","district_id":"940302","name":"Epo Obano"},{"id":"9403022007","district_id":"940302","name":"Towauwo"},{"id":"9403022008","district_id":"940302","name":"Wiyogei"},{"id":"9403022009","district_id":"940302","name":"Ekinauwo"},{"id":"9403022010","district_id":"940302","name":"Kigodide"},{"id":"9403022011","district_id":"940302","name":"Putakogopa"},{"id":"9403022012","district_id":"940302","name":"Waukotopa"},{"id":"9403022013","district_id":"940302","name":"Digiugii"}]