[{"id":"130701","regency_id":"1307","name":"Suliki"},{"id":"130702","regency_id":"1307","name":"Guguak"},{"id":"130703","regency_id":"1307","name":"Payakumbuh"},{"id":"130704","regency_id":"1307","name":"Luak"},{"id":"130705","regency_id":"1307","name":"Harau"},{"id":"130706","regency_id":"1307","name":"Pangkalan Koto Baru"},{"id":"130707","regency_id":"1307","name":"Kapur IX"},{"id":"130708","regency_id":"1307","name":"Gunuang Omeh"},{"id":"130709","regency_id":"1307","name":"Lareh Sago Halaban"},{"id":"130710","regency_id":"1307","name":"Situjuah Limo Nagari"},{"id":"130711","regency_id":"1307","name":"Mungka"},{"id":"130712","regency_id":"1307","name":"Bukik Barisan"},{"id":"130713","regency_id":"1307","name":"Akabiluru"}]