[{"id":"317401","regency_id":"3174","name":"Tebet"},{"id":"317402","regency_id":"3174","name":"Setiabudi"},{"id":"317403","regency_id":"3174","name":"Mampang Prapatan"},{"id":"317404","regency_id":"3174","name":"Pasar Minggu"},{"id":"317405","regency_id":"3174","name":"Kebayoran Lama"},{"id":"317406","regency_id":"3174","name":"Cilandak"},{"id":"317407","regency_id":"3174","name":"Kebayoran Baru"},{"id":"317408","regency_id":"3174","name":"Pancoran"},{"id":"317409","regency_id":"3174","name":"Jagakarsa"},{"id":"317410","regency_id":"3174","name":"Pesanggrahan"}]