[{"id":"320201","regency_id":"3202","name":"Palabuhanratu"},{"id":"320202","regency_id":"3202","name":"Simpenan"},{"id":"320203","regency_id":"3202","name":"Cikakak"},{"id":"320204","regency_id":"3202","name":"Bantargadung"},{"id":"320205","regency_id":"3202","name":"Cisolok"},{"id":"320206","regency_id":"3202","name":"Cikidang"},{"id":"320207","regency_id":"3202","name":"Lengkong"},{"id":"320208","regency_id":"3202","name":"Jampangtengah"},{"id":"320209","regency_id":"3202","name":"Warungkiara"},{"id":"320210","regency_id":"3202","name":"Cikembar"},{"id":"320211","regency_id":"3202","name":"Cibadak"},{"id":"320212","regency_id":"3202","name":"Nagrak"},{"id":"320213","regency_id":"3202","name":"Parungkuda"},{"id":"320214","regency_id":"3202","name":"Bojonggenteng"},{"id":"320215","regency_id":"3202","name":"Parakansalak"},{"id":"320216","regency_id":"3202","name":"Cicurug"},{"id":"320217","regency_id":"3202","name":"Cidahu"},{"id":"320218","regency_id":"3202","name":"Kalapanunggal"},{"id":"320219","regency_id":"3202","name":"Kabandungan"},{"id":"320220","regency_id":"3202","name":"Waluran"},{"id":"320221","regency_id":"3202","name":"Jampangkulon"},{"id":"320222","regency_id":"3202","name":"Ciemas"},{"id":"320223","regency_id":"3202","name":"Kalibunder"},{"id":"320224","regency_id":"3202","name":"Surade"},{"id":"320225","regency_id":"3202","name":"Cibitung"},{"id":"320226","regency_id":"3202","name":"Ciracap"},{"id":"320227","regency_id":"3202","name":"Gunungguruh"},{"id":"320228","regency_id":"3202","name":"Cicantayan"},{"id":"320229","regency_id":"3202","name":"Cisaat"},{"id":"320230","regency_id":"3202","name":"Kadudampit"},{"id":"320231","regency_id":"3202","name":"Caringin"},{"id":"320232","regency_id":"3202","name":"Sukabumi"},{"id":"320233","regency_id":"3202","name":"Sukaraja"},{"id":"320234","regency_id":"3202","name":"Kebonpedes"},{"id":"320235","regency_id":"3202","name":"Cireunghas"},{"id":"320236","regency_id":"3202","name":"Sukalarang"},{"id":"320237","regency_id":"3202","name":"Pabuaran"},{"id":"320238","regency_id":"3202","name":"Purabaya"},{"id":"320239","regency_id":"3202","name":"Nyalindung"},{"id":"320240","regency_id":"3202","name":"Gegerbitung"},{"id":"320241","regency_id":"3202","name":"Sagaranten"},{"id":"320242","regency_id":"3202","name":"Curugkembar"},{"id":"320243","regency_id":"3202","name":"Cidolog"},{"id":"320244","regency_id":"3202","name":"Cidadap"},{"id":"320245","regency_id":"3202","name":"Tegalbuleud"},{"id":"320246","regency_id":"3202","name":"Cimanggu"},{"id":"320247","regency_id":"3202","name":"Ciambar"}]